odoo8_addon_stock_ownership_by_move-8.0.0.1.0.99.dev10-nspkg.pth
odoo_addons/stock_ownership_by_move/README.rst
odoo_addons/stock_ownership_by_move/__init__.py
odoo_addons/stock_ownership_by_move/__openerp__.py
odoo_addons/stock_ownership_by_move/i18n/de.po
odoo_addons/stock_ownership_by_move/i18n/es.po
odoo_addons/stock_ownership_by_move/i18n/es_AR.po
odoo_addons/stock_ownership_by_move/i18n/fi.po
odoo_addons/stock_ownership_by_move/i18n/fr.po
odoo_addons/stock_ownership_by_move/i18n/it.po
odoo_addons/stock_ownership_by_move/i18n/pt_BR.po
odoo_addons/stock_ownership_by_move/i18n/sl.po
odoo_addons/stock_ownership_by_move/i18n/stock_ownership_by_move.pot
odoo_addons/stock_ownership_by_move/i18n/tr.po
odoo_addons/stock_ownership_by_move/i18n/tr_TR.po
odoo_addons/stock_ownership_by_move/model/__init__.py
odoo_addons/stock_ownership_by_move/model/picking.py
odoo_addons/stock_ownership_by_move/security/group.xml
odoo_addons/stock_ownership_by_move/static/description/icon.png
odoo_addons/stock_ownership_by_move/tests/__init__.py
odoo_addons/stock_ownership_by_move/tests/test_picking_to_pack_ops.py
odoo_addons/stock_ownership_by_move/view/move.xml
odoo_addons/stock_ownership_by_move/view/picking.xml
odoo_addons/stock_ownership_by_move/view/wizard_transfer.xml
odoo8_addon_stock_ownership_by_move-8.0.0.1.0.99.dev10.dist-info/METADATA
odoo8_addon_stock_ownership_by_move-8.0.0.1.0.99.dev10.dist-info/WHEEL
odoo8_addon_stock_ownership_by_move-8.0.0.1.0.99.dev10.dist-info/namespace_packages.txt
odoo8_addon_stock_ownership_by_move-8.0.0.1.0.99.dev10.dist-info/top_level.txt
odoo8_addon_stock_ownership_by_move-8.0.0.1.0.99.dev10.dist-info/RECORD
